{
  "project_info": {
    "project_number": "526135019276",
    "project_id": "adventure-log-f04da",
    "storage_bucket": "adventure-log-f04da.firebasestorage.app"
  },
  "client": [
    {
      "client_info": {
        "mobilesdk_app_id": "1:526135019276:android:86ebafc3ef7030f1c0ab29",
        "android_client_info": {
          "package_name": "adventurelog.com"
        }
      },
      "oauth_client": [
        {
          "client_id": "526135019276-ci4ee2haa2ocuo8f5sn1cldig0g1e1ej.apps.googleusercontent.com",
          "client_type": 3
        }
      ],
      "api_key": [
        {
          "current_key": "AIzaSyDroXARqUK9AStqjrFfW1MlYXML30foiqI"
        }
      ],
      "services": {
        "appinvite_service": {
          "other_platform_oauth_client": [
            {
              "client_id": "526135019276-ci4ee2haa2ocuo8f5sn1cldig0g1e1ej.apps.googleusercontent.com",
              "client_type": 3
            }
          ]
        }
      }
    },
    {
      "client_info": {
        "mobilesdk_app_id": "1:526135019276:android:09fdca415bbf6470c0ab29",
        "android_client_info": {
          "package_name": "com.example.adventure_log"
        }
      },
      "oauth_client": [
        {
          "client_id": "526135019276-ci4ee2haa2ocuo8f5sn1cldig0g1e1ej.apps.googleusercontent.com",
          "client_type": 3
        }
      ],
      "api_key": [
        {
          "current_key": "AIzaSyDroXARqUK9AStqjrFfW1MlYXML30foiqI"
        }
      ],
      "services": {
        "appinvite_service": {
          "other_platform_oauth_client": [
            {
              "client_id": "526135019276-ci4ee2haa2ocuo8f5sn1cldig0g1e1ej.apps.googleusercontent.com",
              "client_type": 3
            }
          ]
        }
      }
    }
  ],
  "configuration_version": "1"
}